Metadata-Version: 2.1
Name: OpenGesture
Version: 1.0.2
Summary: Customizable numerical hand recognition
Home-page: https://gitlab.com/esrh/cvgesture-functions
Author: Gatlen Culp, Eshan Ramesh
License: UNKNOWN
Platform: UNKNOWN
Classifier: Programming Language :: Python :: 3
Classifier: Operating System :: OS Independent
Requires-Python: >=3.6
